circle/__init__.py
circle/web3/__init__.py
circle/web3/configurations/__init__.py
circle/web3/configurations/api_client.py
circle/web3/configurations/api_response.py
circle/web3/configurations/configuration.py
circle/web3/configurations/exceptions.py
circle/web3/configurations/py.typed
circle/web3/configurations/rest.py
circle/web3/configurations/api/__init__.py
circle/web3/configurations/api/developer_account_api.py
circle/web3/configurations/api/faucet_api.py
circle/web3/configurations/api/health_api.py
circle/web3/configurations/api/monitor_tokens_api.py
circle/web3/configurations/api/webhook_subscriptions_api.py
circle/web3/configurations/models/__init__.py
circle/web3/configurations/models/bad_request_response.py
circle/web3/configurations/models/blockchain.py
circle/web3/configurations/models/create_monitored_tokens_request.py
circle/web3/configurations/models/create_subscription_request.py
circle/web3/configurations/models/delete_monitored_tokens_request.py
circle/web3/configurations/models/entity_config.py
circle/web3/configurations/models/entity_config_data.py
circle/web3/configurations/models/error.py
circle/web3/configurations/models/faucet_request.py
circle/web3/configurations/models/monitored_tokens.py
circle/web3/configurations/models/monitored_tokens_data.py
circle/web3/configurations/models/not_authorized_response.py
circle/web3/configurations/models/not_found_response.py
circle/web3/configurations/models/notification_signature_public_key.py
circle/web3/configurations/models/notification_signature_public_key_data.py
circle/web3/configurations/models/notification_type.py
circle/web3/configurations/models/ping.py
circle/web3/configurations/models/public_key.py
circle/web3/configurations/models/public_key_data.py
circle/web3/configurations/models/subscription.py
circle/web3/configurations/models/subscription_response.py
circle/web3/configurations/models/subscriptions.py
circle/web3/configurations/models/testnet_blockchain.py
circle_configurations-9.1.0.dist-info/METADATA
circle_configurations-9.1.0.dist-info/WHEEL
circle_configurations-9.1.0.dist-info/top_level.txt
circle_configurations-9.1.0.dist-info/RECORD
